SocialDictionary/__init__.py
SocialDictionary/sentiment_analysis.py
SocialDictionary/Dados/dataset_complete_with_emotions.csv
libname/__init__.py
libname/sentiment_analysis.py
SocialDictionary-1.3.dist-info/METADATA
SocialDictionary-1.3.dist-info/WHEEL
SocialDictionary-1.3.dist-info/top_level.txt
SocialDictionary-1.3.dist-info/RECORD
