Metadata-Version: 2.1
Name: SocialDictionary
Version: 1.3
Summary: This package is used to analyse sentiment, and emojis are also included in this sentiment analysis. The package uses a pre-trained model to assign an emotion to the emojis 
Home-page: UNKNOWN
Author: Goncalo Silva
Author-email: gresi2001@gmail.com
License: UNKNOWN
Keywords: python,text,EmoRoBERTa,sentiment analysis,emojis
Platform: UNKNOWN
Classifier: Development Status :: 1 - Planning
Classifier: Intended Audience :: Developers
Classifier: Programming Language :: Python :: 3
Classifier: License :: OSI Approved :: MIT License
Classifier: Operating System :: Unix
Classifier: Operating System :: MacOS :: MacOS X
Classifier: Operating System :: Microsoft :: Windows
Requires-Dist: pandas
Requires-Dist: nltk
Requires-Dist: emoji
Requires-Dist: googletrans
